{
  "_class": "page",
  "do_objectID": "4C5FBB64-4DD0-4C63-A9B2-41AED5C924B6",
  "booleanOperation": -1,
  "isFixedToViewport": false,
  "isFlippedHorizontal": false,
  "isFlippedVertical": false,
  "isLocked": false,
  "isVisible": true,
  "layerListExpandedType": 0,
  "maintainScrollPosition": false,
  "name": "Page 1",
  "nameIsFixed": false,
  "resizingConstraint": 63,
  "resizingType": 0,
  "rotation": 0,
  "shouldBreakMaskChain": false,
  "exportOptions": {
    "_class": "exportOptions",
    "includedLayerIds": [],
    "layerOptions": 0,
    "shouldTrim": false,
    "exportFormats": []
  },
  "frame": {
    "_class": "rect",
    "constrainProportions": false,
    "height": 0,
    "width": 0,
    "x": 0,
    "y": 0
  },
  "clippingMaskMode": 0,
  "hasClippingMask": false,
  "style": {
    "_class": "style",
    "endMarkerType": 0,
    "miterLimit": 10,
    "startMarkerType": 0,
    "windingRule": 1,
    "blur": {
      "_class": "blur",
      "isEnabled": false,
      "center": "{0.5, 0.5}",
      "motionAngle": 0,
      "radius": 10,
      "saturation": 1,
      "type": 0
    },
    "borderOptions": {
      "_class": "borderOptions",
      "isEnabled": true,
      "dashPattern": [],
      "lineCapStyle": 0,
      "lineJoinStyle": 0
    },
    "borders": [],
    "colorControls": {
      "_class": "colorControls",
      "isEnabled": true,
      "brightness": 0,
      "contrast": 1,
      "hue": 0,
      "saturation": 1
    },
    "contextSettings": {
      "_class": "graphicsContextSettings",
      "blendMode": 0,
      "opacity": 1
    },
    "fills": [],
    "innerShadows": [],
    "shadows": []
  },
  "hasClickThrough": true,
  "groupLayout": { "_class": "MSImmutableFreeformGroupLayout" },
  "layers": [],
  "includeInCloudUpload": true,
  "horizontalRulerData": { "_class": "rulerData", "base": 0, "guides": [] },
  "verticalRulerData": { "_class": "rulerData", "base": 0, "guides": [] }
}
