{
  "_class": "document",
  "do_objectID": "D00DCB25-B560-4B34-9B63-016620DD2540",
  "assets": {
    "_class": "assetCollection",
    "colorAssets": [],
    "gradientAssets": [],
    "imageCollection": { "_class": "imageCollection", "images": {} },
    "images": [],
    "colors": [],
    "gradients": []
  },
  "colorSpace": 0,
  "currentPageIndex": 0,
  "foreignLayerStyles": [],
  "foreignSymbols": [],
  "foreignTextStyles": [],
  "layerStyles": { "_class": "sharedStyleContainer", "objects": [] },
  "layerSymbols": { "_class": "symbolContainer", "objects": [] },
  "layerTextStyles": { "_class": "sharedTextStyleContainer", "objects": [] },
  "pages": [
    {
      "_class": "MSJSONFileReference",
      "_ref_class": "MSImmutablePage",
      "_ref": "pages/0136CF98-67E7-41EC-AE0B-55BF5D64B24D"
    }
  ]
}
